[
    {
       "value":"10",
       "display":"10"
    },
    {
       "value":"11",
       "display":"11"
    },
    {
       "value":"21",
       "display":"21"
    },
    {
       "value":"22",
       "display":"22"
    },
    {
       "value":"31",
       "display":"31"
    },
    {
       "value":"40",
       "display":"40"
    },
    {
       "value":"45",
       "display":"45"
    },
    {
       "value":"48",
       "display":"48"
    },
    {
       "value":"51",
       "display":"51"
    },
    {
       "value":"53",
       "display":"53"
    },
    {
       "value":"54",
       "display":"54"
    },
    {
       "value":"61",
       "display":"61"
    },
    {
       "value":"63",
       "display":"63"
    },
    {
       "value":"68",
       "display":"68"
    },
    {
       "value":"71",
       "display":"71"
    },
    {
       "value":"77",
       "display":"77"
    },
    {
       "value":"78",
       "display":"78"
    },
    {
       "value":"00",
       "display":"00"
    },
    {
       "value":"01",
       "display":"01"
    },
    {
       "value":"07",
       "display":"07"
    },
    {
       "value":"23",
       "display":"23"
    },
    {
       "value":"42",
       "display":"42"
    },
    {
       "value":"43",
       "display":"43"
    },
    {
       "value":"44",
       "display":"44"
    },
    {
       "value":"46",
       "display":"46"
    },
    {
       "value":"76",
       "display":"76"
    },
    {
       "value":"95",
       "display":"95"
    },
    {
       "value":"96",
       "display":"96"
    }]